Metadata-Version: 2.1
Name: REPIC
Version: 1.3
Summary: Read Evaluate Print in Comments
Home-page: https://github.com/dpinney/REPIC/
Author: David Pinney
Author-email: david@pinney.org
License: UNKNOWN
Platform: UNKNOWN
